{ 
	"zombies" : [
		{
			"position" : [
				{"x" : 250, "y" : 200},
				{"x" : 250, "y" : 250}
			],
			"speed" : 100 
		},
		{
			"position" : [
				{"x" : 300, "y" : 300},
				{"x" : 350, "y" : 300},
				{"x" : 325, "y" : 100}
			],
			"speed" : 150 
		}
	],
	"checkpoints" : [
		{
			"spawnpoints" : [
				{"x": 80, "y": 75},
				{"x": 80, "y": 155},
				{"x": 80, "y": 235},
				{"x": 80, "y": 315}
			], 
			"dimensions" : {"x0" : 0, "width" : 10, "y0" : 0, "height" : 10}
		},
		{ 
			"spawnpoints" : [
				{"x": 0, "y": 0},
				{"x": 0, "y": 1},
				{"x": 0, "y": 2},
				{"x": 0, "y": 3}
			],
			"dimensions" : {"x0" : 10, "width" : 10, "y0" : 10, "height" : 10}
		}
	]
}
